async_udemy_dl.py
async_udemy_dl-0.1.1.dist-info/LICENSE
async_udemy_dl-0.1.1.dist-info/METADATA
async_udemy_dl-0.1.1.dist-info/WHEEL
async_udemy_dl-0.1.1.dist-info/entry_points.txt
async_udemy_dl-0.1.1.dist-info/top_level.txt
async_udemy_dl-0.1.1.dist-info/RECORD
