Metadata-Version: 2.1
Name: async-udemy-dl
Version: 0.1.1
Summary: simple script to asynchronously download udemy course
Home-page: https://github.com/Firkraag/async-udemy-dl
Author: wq2
Author-email: smilingwang2@gmail.com
License: UNKNOWN
Platform: UNKNOWN
Classifier: Programming Language :: Python :: 3.7
Classifier: License :: OSI Approved :: MIT License
Classifier: Operating System :: OS Independent
Requires-Python: >=3.7
Requires-Dist: requests
Requires-Dist: aiohttp
